sqlalchemy_mutablesoup/__init__.py
sqlalchemy_mutablesoup-0.0.9.dist-info/LICENSE
sqlalchemy_mutablesoup-0.0.9.dist-info/METADATA
sqlalchemy_mutablesoup-0.0.9.dist-info/WHEEL
sqlalchemy_mutablesoup-0.0.9.dist-info/top_level.txt
sqlalchemy_mutablesoup-0.0.9.dist-info/RECORD
