Metadata-Version: 2.1
Name: sqlalchemy-mutablesoup
Version: 0.0.9
Summary: Mutable BeautifulSoup database type
Home-page: https://dsbowen.github.io/sqlalchemy-mutablesoup
Author: Dillon Bowen
Author-email: dsbowen@wharton.upenn.edu
License: UNKNOWN
Platform: UNKNOWN
Classifier: Programming Language :: Python :: 3
Classifier: License :: OSI Approved :: MIT License
Classifier: Operating System :: OS Independent
Requires-Python: >=3.6
Requires-Dist: bs4 (>=0.0.1)
Requires-Dist: flask (>=1.1.1)
Requires-Dist: sqlalchemy (>=1.3.12)
